di_u3/__init__.py
di_u3/principal.py
di_u3/Conexion_BBDD/__init__.py
di_u3/Conexion_BBDD/connectionBBDD.py
di_u3/Controladores/__init__.py
di_u3/Controladores/modificarReservaControlador.py
di_u3/Controladores/mostrarReservasControlador.py
di_u3/Controladores/reservarControlador.py
di_u3/Imagenes/__init__.py
di_u3/Vistas/__init__.py
di_u3/Vistas/miHotel.py
di_u3/Vistas/modificarReserva.py
di_u3/Vistas/mostrarReservas.py
di_u3/Vistas/reservar.py
lopez_gonzalez_nuria_DI03_Tarea-0.1.0.dist-info/METADATA
lopez_gonzalez_nuria_DI03_Tarea-0.1.0.dist-info/WHEEL
lopez_gonzalez_nuria_DI03_Tarea-0.1.0.dist-info/top_level.txt
lopez_gonzalez_nuria_DI03_Tarea-0.1.0.dist-info/RECORD
