Metadata-Version: 2.2
Name: lopez_gonzalez_nuria_DI03_Tarea
Version: 0.1.0
Summary: Reserva de salones para eventos en hotel MiHotel
Home-page: 
Author: Nuria Lopez Gonzalez
Author-email: nuria.lopezg1@gmail.com
Classifier: Programming Language :: Python :: 3
Classifier: License :: OSI Approved :: MIT License
Classifier: Operating System :: OS Independent
Requires-Dist: PySide6
Dynamic: author
Dynamic: author-email
Dynamic: classifier
Dynamic: description
Dynamic: description-content-type
Dynamic: requires-dist
Dynamic: summary
